{
    "title": "Chain of Responsibility",
    "summary": "Chain of Responsibility is a behavioral design pattern that allows an object to pass a request along a chain of potential handlers until one of them handles the request. This pattern decouples the sender and receiver of a request, allowing for more flexible and maintainable code.",
    "author": "KyungJoon Lee",
    "date": "2025-06-11T15:40:11.000Z",
    "tags": ["Programming Pattern", "C++", "Chain of Responsibility", "Behaviroal Pattern"]
}